<?xml version="1.0" encoding="utf-8" ?><dwsync><file name="domains_get.tpl" server="ftp.icellphones.com//public_html/" local="3672405214" remote="3680315340" Dst="-1" /><file name="webspaces_get_by_owner_id.tpl" server="ftp.icellphones.com//public_html/" local="3672405214" remote="3680315340" Dst="-1" /><file name="customer_set_password.tpl" server="ftp.icellphones.com//public_html/" local="3672405214" remote="3680315340" Dst="-1" /><file name="webspaces_get.tpl" server="ftp.icellphones.com//public_html/" local="3672405214" remote="3680315340" Dst="-1" /><file name="customer_del.tpl" server="ftp.icellphones.com//public_html/" local="3672405214" remote="3680315340" Dst="-1" /><file name="reseller_set_password.tpl" server="ftp.icellphones.com//public_html/" local="3672405214" remote="3680315340" Dst="-1" /><file name="webspace_add.tpl" server="ftp.icellphones.com//public_html/" local="3672405214" remote="3680315340" Dst="-1" /><file name="webspace_set_ip.tpl" server="ftp.icellphones.com//public_html/" local="3672405214" remote="3680315340" Dst="-1" /><file name="webspace_set_password.tpl" server="ftp.icellphones.com//public_html/" local="3672405214" remote="3680315340" Dst="-1" /><file name="webspace_get_by_name.tpl" server="ftp.icellphones.com//public_html/" local="3672405214" remote="3680315340" Dst="-1" /><file name="customer_ippool_add_ip.tpl" server="ftp.icellphones.com//public_html/" local="3672405214" remote="3680315340" Dst="-1" /><file name="domain_usage_get_by_name.tpl" server="ftp.icellphones.com//public_html/" local="3672405214" remote="3680315340" Dst="-1" /><file name="customer_get_by_login.tpl" server="ftp.icellphones.com//public_html/" local="3672405214" remote="3680315340" Dst="-1" /><file name="customer_add.tpl" server="ftp.icellphones.com//public_html/" local="3672405214" remote="3680315340" Dst="-1" /><file name="webspace_del.tpl" server="ftp.icellphones.com//public_html/" local="3672405214" remote="3680315340" Dst="-1" /><file name="ip_get.tpl" server="ftp.icellphones.com//public_html/" local="3672405214" remote="3680315340" Dst="-1" /><file name="webspace_set_status.tpl" server="ftp.icellphones.com//public_html/" local="3672405214" remote="3680315340" Dst="-1" /><file name="server_getProtos.tpl" server="ftp.icellphones.com//public_html/" local="3672405214" remote="3680315340" Dst="-1" /></dwsync>