<?xml version="1.0" encoding="utf-8" ?><dwsync><file name="wp-feature.png" server="ftp.icellphones.com//public_html/" local="3672405212" remote="3680339220" Dst="-1" /><file name="api-feature.png" server="ftp.icellphones.com//public_html/" local="3672405212" remote="3680339220" Dst="-1" /><file name="daily-backups-feature.png" server="ftp.icellphones.com//public_html/" local="3672405212" remote="3680339220" Dst="-1" /><file name="malware-feature.png" server="ftp.icellphones.com//public_html/" local="3672405212" remote="3680339220" Dst="-1" /><file name="unlimited-files-feature.png" server="ftp.icellphones.com//public_html/" local="3672405212" remote="3680339220" Dst="-1" /><file name="click-restore-feature.png" server="ftp.icellphones.com//public_html/" local="3672405212" remote="3680339220" Dst="-1" /><file name="file-monitoring-feature.png" server="ftp.icellphones.com//public_html/" local="3672405212" remote="3680339220" Dst="-1" /><file name="email-feature.png" server="ftp.icellphones.com//public_html/" local="3672405212" remote="3680339220" Dst="-1" /><file name="servers-feature.png" server="ftp.icellphones.com//public_html/" local="3672405212" remote="3680339220" Dst="-1" /></dwsync>